sportscraper/__init__.py
sportscraper/__main__.py
sportscraper/cli.py
sportscraper/fifaindex.py
sportscraper/utils.py
sportscraper_yarkin-0.1.2.dist-info/METADATA
sportscraper_yarkin-0.1.2.dist-info/WHEEL
sportscraper_yarkin-0.1.2.dist-info/entry_points.txt
sportscraper_yarkin-0.1.2.dist-info/licenses/LICENSE
sportscraper_yarkin-0.1.2.dist-info/RECORD
